Metadata-Version: 2.1
Name: datasette-sqlite-fts4
Version: 0.3.2
Summary: Datasette plugin exposing SQL functions from sqlite-fts4
Home-page: https://github.com/simonw/datasette-sqlite-fts4
Author: Simon Willison
License: Apache License, Version 2.0
Project-URL: Issues, https://github.com/simonw/datasette-sqlite-fts4/issues
Project-URL: CI, https://github.com/simonw/datasette-sqlite-fts4/actions
Project-URL: Changelog, https://github.com/simonw/datasette-sqlite-fts4/releases
Classifier: Framework :: Datasette
Classifier: License :: OSI Approved :: Apache Software License
Requires-Python: >=3.7
License-File: LICENSE
Requires-Dist: datasette
Requires-Dist: sqlite-fts4 (>=1.0.3)
Provides-Extra: test
Requires-Dist: pytest ; extra == 'test'
Requires-Dist: pytest-asyncio ; extra == 'test'
